Workbook

Sheet Dashboard

Sheet Ratio Analysis
A1: Coca-Cola (KO)
A3: Metric | B3: FY2022 | C3: FY2023 | D3: FY2024
A4: Current Ratio | B4: ='KO Data'!B8 / 'KO Data'!B10 -> 1.1453559 | C4: ='KO Data'!C8 / 'KO Data'!C10 -> 1.1341055 | D4: ='KO Data'!D8 / 'KO Data'!D10 -> 1.0296249
A5: Working Capital | B5: ='KO Data'!B8 - 'KO Data'!B10 -> 2867 | C5: ='KO Data'!C8 - 'KO Data'!C10 -> 3161 | D5: ='KO Data'!D8 - 'KO Data'!D10 -> 748
A6: Debt-to-Equity | B6: ='KO Data'!B9 / 'KO Data'!B11 -> 2.5918454 | C6: ='KO Data'!C9 / 'KO Data'!C11 -> 2.5554221 | D6: ='KO Data'!D9 / 'KO Data'!D11 -> 2.812718
A7: Debt Ratio | B7: ='KO Data'!B9 / 'KO Data'!B7 -> 0.72159158 | C7: ='KO Data'!C9 / 'KO Data'!C7 -> 0.71873945 | D7: ='KO Data'!D9 / 'KO Data'!D7 -> 0.73771992
A8: Net Profit Margin | B8: ='KO Data'!B6 / 'KO Data'!B5 -> 0.22188634 | C8: ='KO Data'!C6 / 'KO Data'!C5 -> 0.23416532 | D8: ='KO Data'!D6 / 'KO Data'!D5 -> 0.2258983
A9: Asset Turnover | B9: ='KO Data'!B5 / 'KO Data'!B7 -> 0.46359001 | C9: ='KO Data'!C5 / 'KO Data'!C7 -> 0.46829678 | D9: ='KO Data'!D5 / 'KO Data'!D7 -> 0.46804046
A10: Equity Multiplier | B10: ='KO Data'!B7 / 'KO Data'!B11 -> 3.5918454 | C10: ='KO Data'!C7 / 'KO Data'!C11 -> 3.5554221 | D10: ='KO Data'!D7 / 'KO Data'!D11 -> 3.812718
A11: ROA | B11: ='KO Data'!B6 / 'KO Data'!B7 -> 0.10286429 | C11: ='KO Data'!C6 / 'KO Data'!C7 -> 0.10965886 | D11: ='KO Data'!D6 / 'KO Data'!D7 -> 0.10572954
A12: ROE | B12: ='KO Data'!B6 / 'KO Data'!B11 -> 0.36947262 | C12: ='KO Data'!C6 / 'KO Data'!C11 -> 0.38988355 | D12: ='KO Data'!D6 / 'KO Data'!D11 -> 0.40311694
A14: PepsiCo (PEP)
A15: Metric | B15: FY2022 | C15: FY2023 | D15: FY2024
A16: Current Ratio | B16: ='PEP Data'!B8 / 'PEP Data'!B10 -> 0.80414411 | C16: ='PEP Data'!C8 / 'PEP Data'!C10 -> 0.85158151 | D16: ='PEP Data'!D8 / 'PEP Data'!D10 -> 0.81893709
A17: Working Capital | B17: ='PEP Data'!B8 - 'PEP Data'!B10 -> -5246 | C17: ='PEP Data'!C8 - 'PEP Data'!C10 -> -4697 | D17: ='PEP Data'!D8 - 'PEP Data'!D10 -> -5710
A18: Debt-to-Equity | B18: ='PEP Data'!B9 / 'PEP Data'!B11 -> 4.3370578 | C18: ='PEP Data'!C9 / 'PEP Data'!C11 -> 4.3922305 | D18: ='PEP Data'!D9 / 'PEP Data'!D11 -> 4.473942
A19: Debt Ratio | B19: ='PEP Data'!B9 / 'PEP Data'!B7 -> 0.81263085 | C19: ='PEP Data'!C9 / 'PEP Data'!C7 -> 0.81454799 | D19: ='PEP Data'!D9 / 'PEP Data'!D7 -> 0.8173163
A20: Net Profit Margin | B20: ='PEP Data'!B6 / 'PEP Data'!B5 -> 0.10313455 | C20: ='PEP Data'!C6 / 'PEP Data'!C5 -> 0.09920084 | D20: ='PEP Data'!D6 / 'PEP Data'!D5 -> 0.10427417
A21: Asset Turnover | B21: ='PEP Data'!B5 / 'PEP Data'!B7 -> 0.93713864 | C21: ='PEP Data'!C5 / 'PEP Data'!C7 -> 0.91020449 | D21: ='PEP Data'!D5 / 'PEP Data'!D7 -> 0.92346205
A22: Equity Multiplier | B22: ='PEP Data'!B7 / 'PEP Data'!B11 -> 5.3370578 | C22: ='PEP Data'!C7 / 'PEP Data'!C11 -> 5.3922305 | D22: ='PEP Data'!D7 / 'PEP Data'!D11 -> 5.473942
A23: ROA | B23: ='PEP Data'!B6 / 'PEP Data'!B7 -> 0.096651372 | C23: ='PEP Data'!C6 / 'PEP Data'!C7 -> 0.090293049 | D23: ='PEP Data'!D6 / 'PEP Data'!D7 -> 0.096293243
A24: ROE | B24: ='PEP Data'!B6 / 'PEP Data'!B11 -> 0.51583396 | C24: ='PEP Data'!C6 / 'PEP Data'!C11 -> 0.48688094 | D24: ='PEP Data'!D6 / 'PEP Data'!D11 -> 0.52710363

Sheet Chart Source
A1: Mini Chart Source
A3: Metric | B3: FY2022 | C3: FY2023 | D3: FY2024
A4: KO Revenue | B4: ='KO Data'!B5 -> 43004 | C4: ='KO Data'!C5 -> 45754 | D4: ='KO Data'!D5 -> 47061
A5: PEP Revenue | B5: ='PEP Data'!B5 -> 86392 | C5: ='PEP Data'!C5 -> 91471 | D5: ='PEP Data'!D5 -> 91854
A6: KO Net Profit Margin | B6: ='Ratio Analysis'!B8 -> 0.22188634 | C6: ='Ratio Analysis'!C8 -> 0.23416532 | D6: ='Ratio Analysis'!D8 -> 0.2258983
A7: PEP Net Profit Margin | B7: ='Ratio Analysis'!B20 -> 0.10313455 | C7: ='Ratio Analysis'!C20 -> 0.09920084 | D7: ='Ratio Analysis'!D20 -> 0.10427417
A8: KO Current Ratio | B8: ='Ratio Analysis'!B4 -> 1.1453559 | C8: ='Ratio Analysis'!C4 -> 1.1341055 | D8: ='Ratio Analysis'!D4 -> 1.0296249
A9: PEP Current Ratio | B9: ='Ratio Analysis'!B16 -> 0.80414411 | C9: ='Ratio Analysis'!C16 -> 0.85158151 | D9: ='Ratio Analysis'!D16 -> 0.81893709
A10: KO ROE | B10: ='Ratio Analysis'!B12 -> 0.36947262 | C10: ='Ratio Analysis'!C12 -> 0.38988355 | D10: ='Ratio Analysis'!D12 -> 0.40311694
A11: PEP ROE | B11: ='Ratio Analysis'!B24 -> 0.51583396 | C11: ='Ratio Analysis'!C24 -> 0.48688094 | D11: ='Ratio Analysis'!D24 -> 0.52710363

Sheet Recommendation
A1: Recommendation: Coca-Cola (KO) vs. PepsiCo (PEP)
A3: Profitability
A4: KO converts sales to profit better than PEP across the three-year period, posting Net Profit Margins of 22.2%, 23.4%, and 22.6% compared to PEP's 10.3%, 9.9%, and 10.4%. PEP, however, relies more heavily on debt to finance its assets than KO does.
A6: Leverage & Return on Equity
A7: Using the DuPont decomposition, PEP's Return on Equity is higher than KO's, but this isn't purely a performance story: PEP has a better Asset Turnover than KO, and is also more leveraged. Both factors, not necessarily superior profitability, are driving PEP's higher ROE.
A9: Liquidity
A10: KO's Current Ratio sits above 1.0, giving it a cushion of short-term assets over short-term liabilities. PEP's Current Ratio sits below 1.0, and its negative Working Capital confirms it, meaning PEP is relying on incoming cash flow rather than existing short-term assets to meet its obligations.
A12: Bottom Line
A13: PEP will generate a higher ROE, but that comes with meaningfully higher financial risk, more leverage and thinner liquidity. Which company is the "better" pick depends on investor risk tolerance: a risk-averse investor prioritizing margin quality and balance sheet safety should lean toward KO, while an investor comfortable trading leverage for a higher equity return could reasonably choose PEP.

Sheet KO Data
A1: The Coca-Cola Company (KO) — Financial Statement Data ($ millions)
A2: Source: SEC 10-K filings, FY2022–FY2024
A4: Line Item | B4: FY2022 | C4: FY2023 | D4: FY2024
A5: Revenue | B5: 43004 | C5: 45754 | D5: 47061
A6: Net Income | B6: 9542 | C6: 10714 | D6: 10631
A7: Total Assets | B7: 92763 | C7: 97703 | D7: 100549
A8: Current Assets | B8: 22591 | C8: 26732 | D8: 25997
A9: Total Liabilities | B9: 66937 | C9: 70223 | D9: 74177
A10: Current Liabilities | B10: 19724 | C10: 23571 | D10: 25249
A11: Total Equity | B11: 25826 | C11: 27480 | D11: 26372

Sheet PEP Data
A1: PepsiCo, Inc. (PEP) — Financial Statement Data ($ millions)
A2: Source: SEC 10-K filings, FY2022–FY2024
A4: Line Item | B4: FY2022 | C4: FY2023 | D4: FY2024
A5: Revenue | B5: 86392 | C5: 91471 | D5: 91854
A6: Net Income | B6: 8910 | C6: 9074 | D6: 9578
A7: Total Assets | B7: 92187 | C7: 100495 | D7: 99467
A8: Current Assets | B8: 21539 | C8: 26950 | D8: 25826
A9: Total Liabilities | B9: 74914 | C9: 81858 | D9: 81296
A10: Current Liabilities | B10: 26785 | C10: 31647 | D10: 31536
A11: Total Equity | B11: 17273 | C11: 18637 | D11: 18171
